{
    "Name": "Chatter Generator",
    "Owner": "Kuuuube",
    "Description": "Add chatter, shake, noise, etc to your tablet input.",
    "PluginVersion": "0.2.2.0",
    "SupportedDriverVersion": "0.6.0.0",
    "RepositoryUrl": "https://github.com/Kuuuube/Chatter_Generator",
    "DownloadUrl": "https://github.com/Kuuuube/Chatter_Generator/releases/download/0.2.2/0.2.2_release_Chatter_Generator.zip",
    "CompressionFormat": "zip",
    "SHA256": "4532ef1e114b8e56b64aec6bf8175bf6f48637043e968eeec9a5b787df1c911b",
    "WikiUrl": "https://github.com/Kuuuube/Chatter_Generator/blob/master/README.md",
    "LicenseIdentifier": "GPL-3.0-only"
}
